README.rst
setup.cfg
setup.py
morph_planningalerts/__init__.py
morph_planningalerts/models.py
morph_planningalerts.egg-info/PKG-INFO
morph_planningalerts.egg-info/SOURCES.txt
morph_planningalerts.egg-info/dependency_links.txt
morph_planningalerts.egg-info/requires.txt
morph_planningalerts.egg-info/top_level.txt